azxbuilder/__init__.py
azxbuilder/cli.py
azxbuilder/generator.py
azxbuilder/models.py
azxbuilder/parser.py
azxbuilder-0.0.1.dist-info/METADATA
azxbuilder-0.0.1.dist-info/WHEEL
azxbuilder-0.0.1.dist-info/top_level.txt
azxbuilder-0.0.1.dist-info/RECORD
