Metadata-Version: 2.4
Name: azxbuilder
Version: 0.0.1
Summary: A revolutionary full-stack application generator.
Author-email: hussain_syrer <h2311065@gmail.com>
Project-URL: Homepage, https://github.com/your-username/azxbuilder
Project-URL: Bug Tracker, https://github.com/your-username/azxbuilder/issues
Classifier: Programming Language :: Python :: 3
Classifier: License :: OSI Approved :: MIT License
Classifier: Operating System :: OS Independent
Requires-Python: >=3.8
Requires-Dist: Jinja2
Requires-Dist: typer[all]
Provides-Extra: test
Requires-Dist: pytest; extra == "test"
